{
  "updatedAt": "2026-05-23T10:56:18.125Z",
  "source": "adsb.lol",
  "aircraft": [
    {
      "id": "ac7a61",
      "callsign": "KYE7525",
      "registration": "N903AR",
      "aircraftType": "B744",
      "lat": 39.750412,
      "lon": -91.537011,
      "trackDeg": 317.08,
      "speedKt": 468.4,
      "altitudeFeet": 40000,
      "altitudeMeters": 12192,
      "renderAltitudeMeters": 3413.76,
      "seenSeconds": 0
    },
    {
      "id": "ac5066",
      "callsign": "SWA2825",
      "registration": "N8929S",
      "aircraftType": "B38M",
      "lat": 39.703903,
      "lon": -91.466317,
      "trackDeg": 52.57,
      "speedKt": 488.6,
      "altitudeFeet": 37000,
      "altitudeMeters": 11277.6,
      "renderAltitudeMeters": 3157.7280000000005,
      "seenSeconds": 0
    },
    {
      "id": "a2bdff",
      "callsign": "EMY3418",
      "registration": "N276NN",
      "aircraftType": "E75L",
      "lat": 38.753621,
      "lon": -91.292358,
      "trackDeg": 260.16,
      "speedKt": 427.3,
      "altitudeFeet": 28000,
      "altitudeMeters": 8534.4,
      "renderAltitudeMeters": 2389.632,
      "seenSeconds": 0.2
    },
    {
      "id": "aac03d",
      "callsign": "ENY4088",
      "registration": "N792JB",
      "aircraftType": "E170",
      "lat": 39.590469,
      "lon": -90.793285,
      "trackDeg": 44.41,
      "speedKt": 478.7,
      "altitudeFeet": 33000,
      "altitudeMeters": 10058.4,
      "renderAltitudeMeters": 2816.3520000000003,
      "seenSeconds": 0.1
    },
    {
      "id": "a22771",
      "callsign": "ENY3828",
      "registration": "N238NN",
      "aircraftType": "E75L",
      "lat": 38.822658,
      "lon": -90.774902,
      "trackDeg": 260.47,
      "speedKt": 410.7,
      "altitudeFeet": 34000,
      "altitudeMeters": 10363.2,
      "renderAltitudeMeters": 2901.6960000000004,
      "seenSeconds": 0
    },
    {
      "id": "a04e00",
      "callsign": "DAL1597",
      "registration": "N119DU",
      "aircraftType": "BCS1",
      "lat": 38.744159,
      "lon": -90.367157,
      "trackDeg": 0,
      "speedKt": 0.1,
      "altitudeFeet": 0,
      "altitudeMeters": 0,
      "renderAltitudeMeters": 280,
      "seenSeconds": 2
    },
    {
      "id": "a41f37",
      "callsign": "DAL1524",
      "registration": "N365DN",
      "aircraftType": "A321",
      "lat": 38.744625,
      "lon": -90.366486,
      "trackDeg": 0,
      "speedKt": 0.6,
      "altitudeFeet": 0,
      "altitudeMeters": 0,
      "renderAltitudeMeters": 280,
      "seenSeconds": 2.5
    },
    {
      "id": "a3f500",
      "callsign": "AAL1926",
      "registration": "N354PT",
      "aircraftType": "B738",
      "lat": 38.742874,
      "lon": -90.363071,
      "trackDeg": 0,
      "speedKt": 0,
      "altitudeFeet": 0,
      "altitudeMeters": 0,
      "renderAltitudeMeters": 280,
      "seenSeconds": 0.3
    },
    {
      "id": "ab385e",
      "callsign": "AAL1004",
      "registration": "N822AW",
      "aircraftType": "A319",
      "lat": 38.742739,
      "lon": -90.362671,
      "trackDeg": 0,
      "speedKt": 0,
      "altitudeFeet": 0,
      "altitudeMeters": 0,
      "renderAltitudeMeters": 280,
      "seenSeconds": 3.1
    },
    {
      "id": "a9942e",
      "callsign": "AAL1308",
      "registration": "N716UW",
      "aircraftType": "A319",
      "lat": 38.742302,
      "lon": -90.361758,
      "trackDeg": 0,
      "speedKt": 0,
      "altitudeFeet": 0,
      "altitudeMeters": 0,
      "renderAltitudeMeters": 280,
      "seenSeconds": 1
    },
    {
      "id": "ac4bfe",
      "callsign": "SWA4489",
      "registration": "N8914Q",
      "aircraftType": "B38M",
      "lat": 38.741703,
      "lon": -90.357239,
      "trackDeg": 0,
      "speedKt": 24.5,
      "altitudeFeet": 0,
      "altitudeMeters": 0,
      "renderAltitudeMeters": 280,
      "seenSeconds": 10.7
    },
    {
      "id": "ac27a6",
      "callsign": "SWA830",
      "registration": "N8820L",
      "aircraftType": "B38M",
      "lat": 38.708496,
      "lon": -90.287376,
      "trackDeg": 121.74,
      "speedKt": 228.1,
      "altitudeFeet": 2650,
      "altitudeMeters": 807.72,
      "renderAltitudeMeters": 280,
      "seenSeconds": 0
    },
    {
      "id": "a19404",
      "callsign": "SWA3102",
      "registration": "N200WN",
      "aircraftType": "B737",
      "lat": 37.57695,
      "lon": -90.110214,
      "trackDeg": 205.03,
      "speedKt": 418.3,
      "altitudeFeet": 38000,
      "altitudeMeters": 11582.400000000001,
      "renderAltitudeMeters": 3243.0720000000006,
      "seenSeconds": 0.1
    },
    {
      "id": "a81045",
      "callsign": "ATN3451",
      "registration": "N619AZ",
      "aircraftType": "B763",
      "lat": 38.085177,
      "lon": -89.967758,
      "trackDeg": 88.34,
      "speedKt": 483.2,
      "altitudeFeet": 37000,
      "altitudeMeters": 11277.6,
      "renderAltitudeMeters": 3157.7280000000005,
      "seenSeconds": 0.2
    },
    {
      "id": "a1ffde",
      "callsign": "N228MT",
      "registration": "N228MT",
      "aircraftType": "EC35",
      "lat": 38.713027,
      "lon": -89.618408,
      "trackDeg": 220.75,
      "speedKt": 124.1,
      "altitudeFeet": 3950,
      "altitudeMeters": 1203.96,
      "renderAltitudeMeters": 337.10880000000003,
      "seenSeconds": 3.1
    },
    {
      "id": "a99b5f",
      "callsign": "SKW6464",
      "registration": "N718SK",
      "aircraftType": "CRJ7",
      "lat": 37.194028,
      "lon": -89.358733,
      "trackDeg": 320.04,
      "speedKt": 467.1,
      "altitudeFeet": 36000,
      "altitudeMeters": 10972.800000000001,
      "renderAltitudeMeters": 3072.3840000000005,
      "seenSeconds": 0
    },
    {
      "id": "a1270f",
      "callsign": "UAL1299",
      "registration": "N17326",
      "aircraftType": "B38M",
      "lat": 38.75404,
      "lon": -89.147339,
      "trackDeg": 96.21,
      "speedKt": 471.8,
      "altitudeFeet": 35000,
      "altitudeMeters": 10668,
      "renderAltitudeMeters": 2987.0400000000004,
      "seenSeconds": 0.2
    },
    {
      "id": "ac17b0",
      "callsign": "SWA690",
      "registration": "N8789Q",
      "aircraftType": "B38M",
      "lat": 38.14682,
      "lon": -88.874895,
      "trackDeg": 332.53,
      "speedKt": 479,
      "altitudeFeet": 34000,
      "altitudeMeters": 10363.2,
      "renderAltitudeMeters": 2901.6960000000004,
      "seenSeconds": 0
    },
    {
      "id": "a76c79",
      "callsign": "DAL393",
      "registration": "N578DN",
      "aircraftType": "A21N",
      "lat": 39.16127,
      "lon": -88.491768,
      "trackDeg": 273.53,
      "speedKt": 438.8,
      "altitudeFeet": 34050,
      "altitudeMeters": 10378.44,
      "renderAltitudeMeters": 2905.9632000000006,
      "seenSeconds": 0
    }
  ]
}
