{
  "updatedAt": "2026-05-18T15:56:07.048Z",
  "source": "Metro St. Louis GTFS-Realtime vehicles",
  "vehicles": [
    {
      "id": "3831",
      "label": "11 Chippewa - WEST",
      "routeId": "19599",
      "tripId": "3356754",
      "lat": 38.58850860595703,
      "lon": -90.244873046875,
      "bearingDeg": 0,
      "speedMps": 0,
      "timestamp": 1779119739,
      "mode": "bus"
    },
    {
      "id": "3833",
      "label": "19 St Louis Ave - WEST",
      "routeId": "19603",
      "tripId": "3357295",
      "lat": 38.67618942260742,
      "lon": -90.27664184570312,
      "bearingDeg": 0,
      "speedMps": 0,
      "timestamp": 1779119734,
      "mode": "bus"
    },
    {
      "id": "3837",
      "label": "49 Lindbergh - NORTH",
      "routeId": "19614",
      "tripId": "3358678",
      "lat": 38.51197814941406,
      "lon": -90.33689880371094,
      "bearingDeg": 0,
      "speedMps": 0,
      "timestamp": 1779119740,
      "mode": "bus"
    },
    {
      "id": "3838",
      "label": "10 Gravois-Lindell - NORTH",
      "routeId": "19598",
      "tripId": "3356457",
      "lat": 38.5807991027832,
      "lon": -90.26776123046875,
      "bearingDeg": 0,
      "speedMps": 0,
      "timestamp": 1779119724,
      "mode": "bus"
    },
    {
      "id": "3843",
      "label": "30 Arsenal - EAST",
      "routeId": "19605",
      "tripId": "3357602",
      "lat": 38.596378326416016,
      "lon": -90.20967102050781,
      "bearingDeg": 0,
      "speedMps": 0,
      "timestamp": 1779119753,
      "mode": "bus"
    },
    {
      "id": "3844",
      "label": "98 Ballas-North Hanley - NORTH",
      "routeId": "19634",
      "tripId": "3361922",
      "lat": 38.639801025390625,
      "lon": -90.4432373046875,
      "bearingDeg": 0,
      "speedMps": 0,
      "timestamp": 1779119698,
      "mode": "bus"
    },
    {
      "id": "3848",
      "label": "57 Manchester - WEST",
      "routeId": "19616",
      "tripId": "3358822",
      "lat": 38.5991096496582,
      "lon": -90.41365814208984,
      "bearingDeg": 0,
      "speedMps": 0,
      "timestamp": 1779119747,
      "mode": "bus"
    },
    {
      "id": "3849",
      "label": "33 Midland - WEST",
      "routeId": "19608",
      "tripId": "3357968",
      "lat": 38.70800018310547,
      "lon": -90.41092681884766,
      "bearingDeg": 0,
      "speedMps": 0,
      "timestamp": 1779119748,
      "mode": "bus"
    },
    {
      "id": "3850",
      "label": "16 City Limits - SOUTH",
      "routeId": "19601",
      "tripId": "3365227",
      "lat": 38.65549850463867,
      "lon": -90.29505157470703,
      "bearingDeg": 0,
      "speedMps": 0,
      "timestamp": 1779119740,
      "mode": "bus"
    },
    {
      "id": "3851",
      "label": "49 Lindbergh - SOUTH",
      "routeId": "19614",
      "tripId": "3358640",
      "lat": 38.508209228515625,
      "lon": -90.38334655761719,
      "bearingDeg": 0,
      "speedMps": 0,
      "timestamp": 1779119700,
      "mode": "bus"
    },
    {
      "id": "3852",
      "label": "49 Lindbergh - SOUTH",
      "routeId": "19614",
      "tripId": "3358652",
      "lat": 38.649269104003906,
      "lon": -90.40548706054688,
      "bearingDeg": 0,
      "speedMps": 0,
      "timestamp": 1779119752,
      "mode": "bus"
    },
    {
      "id": "3853",
      "label": "70 Grand - SOUTH",
      "routeId": "19622",
      "tripId": "3359657",
      "lat": 38.63492965698242,
      "lon": -90.2336196899414,
      "bearingDeg": 0,
      "speedMps": 0,
      "timestamp": 1779119736,
      "mode": "bus"
    },
    {
      "id": "3856",
      "label": "70 Grand - SOUTH",
      "routeId": "19622",
      "tripId": "3359656",
      "lat": 38.5882682800293,
      "lon": -90.24458312988281,
      "bearingDeg": 0,
      "speedMps": 0,
      "timestamp": 1779119752,
      "mode": "bus"
    },
    {
      "id": "6607",
      "label": "76 N Hanley Shuttle - SOUTH",
      "routeId": "19625",
      "tripId": "3360440",
      "lat": 38.78062057495117,
      "lon": -90.33503723144531,
      "bearingDeg": 0,
      "speedMps": 0,
      "timestamp": 1779119734,
      "mode": "bus"
    },
    {
      "id": "6643",
      "label": "35 Rock Road - WEST",
      "routeId": "19610",
      "tripId": "3358131",
      "lat": 38.76087188720703,
      "lon": -90.43094635009766,
      "bearingDeg": 0,
      "speedMps": 0,
      "timestamp": 1779119713,
      "mode": "bus"
    },
    {
      "id": "6703",
      "label": "58 Chesterfield Valley - WEST",
      "routeId": "19617",
      "tripId": "3358946",
      "lat": 38.64609909057617,
      "lon": -90.33873748779297,
      "bearingDeg": 0,
      "speedMps": 0,
      "timestamp": 1779119738,
      "mode": "bus"
    },
    {
      "id": "6705",
      "label": "58 Chesterfield Valley - EAST",
      "routeId": "19617",
      "tripId": "3358923",
      "lat": 38.635101318359375,
      "lon": -90.39791870117188,
      "bearingDeg": 0,
      "speedMps": 0,
      "timestamp": 1779119743,
      "mode": "bus"
    },
    {
      "id": "6707",
      "label": "21 Watson Rd - WEST",
      "routeId": "19604",
      "tripId": "3365107",
      "lat": 38.55569839477539,
      "lon": -90.40574645996094,
      "bearingDeg": 0,
      "speedMps": 0,
      "timestamp": 1779119736,
      "mode": "bus"
    },
    {
      "id": "6709",
      "label": "73 Carondelet - SOUTH",
      "routeId": "19623",
      "tripId": "3360033",
      "lat": 38.511199951171875,
      "lon": -90.31977081298828,
      "bearingDeg": 0,
      "speedMps": 0,
      "timestamp": 1779119744,
      "mode": "bus"
    },
    {
      "id": "6713",
      "label": "11 Chippewa - EAST",
      "routeId": "19599",
      "tripId": "3356701",
      "lat": 38.58964920043945,
      "lon": -90.25695037841797,
      "bearingDeg": 0,
      "speedMps": 0,
      "timestamp": 1779119736,
      "mode": "bus"
    },
    {
      "id": "6716",
      "label": "56 Kirkwood-Webster - EAST",
      "routeId": "19615",
      "tripId": "3358766",
      "lat": 38.591548919677734,
      "lon": -90.33531951904297,
      "bearingDeg": 0,
      "speedMps": 0,
      "timestamp": 1779119750,
      "mode": "bus"
    },
    {
      "id": "6724",
      "label": "57 Manchester - EAST",
      "routeId": "19616",
      "tripId": "3358794",
      "lat": 38.59272003173828,
      "lon": -90.56510162353516,
      "bearingDeg": 0,
      "speedMps": 0,
      "timestamp": 1779119728,
      "mode": "bus"
    },
    {
      "id": "6725",
      "label": "95 Kingshighway - NORTH",
      "routeId": "19632",
      "tripId": "3361623",
      "lat": 38.63901901245117,
      "lon": -90.26175689697266,
      "bearingDeg": 0,
      "speedMps": 0,
      "timestamp": 1779119663,
      "mode": "bus"
    },
    {
      "id": "6726",
      "label": "57 Manchester - WEST",
      "routeId": "19616",
      "tripId": "3358821",
      "lat": 38.59122848510742,
      "lon": -90.59332275390625,
      "bearingDeg": 0,
      "speedMps": 0,
      "timestamp": 1779119482,
      "mode": "bus"
    },
    {
      "id": "6729",
      "label": "57 Manchester - EAST",
      "routeId": "19616",
      "tripId": "3358793",
      "lat": 38.61246871948242,
      "lon": -90.34622955322266,
      "bearingDeg": 0,
      "speedMps": 0,
      "timestamp": 1779119732,
      "mode": "bus"
    },
    {
      "id": "6733",
      "label": "49 Lindbergh - SOUTH",
      "routeId": "19614",
      "tripId": "3358641",
      "lat": 38.722801208496094,
      "lon": -90.33535766601562,
      "bearingDeg": 0,
      "speedMps": 0,
      "timestamp": 1779119713,
      "mode": "bus"
    },
    {
      "id": "6739",
      "label": "10 Gravois-Lindell - NORTH",
      "routeId": "19598",
      "tripId": "3356489",
      "lat": 38.64384841918945,
      "lon": -90.2641372680664,
      "bearingDeg": 0,
      "speedMps": 0,
      "timestamp": 1779119751,
      "mode": "bus"
    },
    {
      "id": "6741",
      "label": "9 Oakville - SOUTH",
      "routeId": "19597",
      "tripId": "3356423",
      "lat": 38.47406005859375,
      "lon": -90.30449676513672,
      "bearingDeg": 0,
      "speedMps": 0,
      "timestamp": 1779119750,
      "mode": "bus"
    },
    {
      "id": "6751",
      "label": "10 Gravois-Lindell - SOUTH",
      "routeId": "19598",
      "tripId": "3356515",
      "lat": 38.63130187988281,
      "lon": -90.20535278320312,
      "bearingDeg": 0,
      "speedMps": 0,
      "timestamp": 1779119736,
      "mode": "bus"
    },
    {
      "id": "6802",
      "label": "32 Dr ML King - WEST",
      "routeId": "19607",
      "tripId": "3357804",
      "lat": 38.66960144042969,
      "lon": -90.27468872070312,
      "bearingDeg": 0,
      "speedMps": 0,
      "timestamp": 1779119740,
      "mode": "bus"
    },
    {
      "id": "6803",
      "label": "40 Broadway-Halls Ferry - NORTH",
      "routeId": "19611",
      "tripId": "3358265",
      "lat": 38.72269821166992,
      "lon": -90.23944854736328,
      "bearingDeg": 0,
      "speedMps": 0,
      "timestamp": 1779119695,
      "mode": "bus"
    },
    {
      "id": "6804",
      "label": "94 Page - WEST",
      "routeId": "19631",
      "tripId": "3361381",
      "lat": 38.668968200683594,
      "lon": -90.29907989501953,
      "bearingDeg": 0,
      "speedMps": 0,
      "timestamp": 1779119754,
      "mode": "bus"
    },
    {
      "id": "6805",
      "label": "94 Page - WEST",
      "routeId": "19631",
      "tripId": "3361382",
      "lat": 38.625850677490234,
      "lon": -90.20188903808594,
      "bearingDeg": 0,
      "speedMps": 0,
      "timestamp": 1779119754,
      "mode": "bus"
    },
    {
      "id": "6806",
      "label": "19 St Louis Ave - EAST",
      "routeId": "19603",
      "tripId": "3357324",
      "lat": 38.63066101074219,
      "lon": -90.19699096679688,
      "bearingDeg": 0,
      "speedMps": 0,
      "timestamp": 1779119732,
      "mode": "bus"
    },
    {
      "id": "6814",
      "label": "94 Page - WEST",
      "routeId": "19631",
      "tripId": "3361397",
      "lat": 38.70309829711914,
      "lon": -90.43115997314453,
      "bearingDeg": 0,
      "speedMps": 0,
      "timestamp": 1779119745,
      "mode": "bus"
    },
    {
      "id": "6816",
      "label": "79 Ferguson-Clayton - NORTH",
      "routeId": "19628",
      "tripId": "3360906",
      "lat": 38.73387145996094,
      "lon": -90.30158233642578,
      "bearingDeg": 0,
      "speedMps": 0,
      "timestamp": 1779119741,
      "mode": "bus"
    },
    {
      "id": "6819",
      "label": "94 Page - EAST",
      "routeId": "19631",
      "tripId": "3361345",
      "lat": 38.685508728027344,
      "lon": -90.34777069091797,
      "bearingDeg": 0,
      "speedMps": 0,
      "timestamp": 1779119731,
      "mode": "bus"
    },
    {
      "id": "6820",
      "label": "91 Olive - EAST",
      "routeId": "19630",
      "tripId": "3361200",
      "lat": 38.67375946044922,
      "lon": -90.45838165283203,
      "bearingDeg": 0,
      "speedMps": 0,
      "timestamp": 1779119736,
      "mode": "bus"
    },
    {
      "id": "6822",
      "label": "35 Rock Road - EAST",
      "routeId": "19610",
      "tripId": "3358095",
      "lat": 38.70389175415039,
      "lon": -90.33782196044922,
      "bearingDeg": 0,
      "speedMps": 0,
      "timestamp": 1779119742,
      "mode": "bus"
    },
    {
      "id": "6833",
      "label": "49 Lindbergh - NORTH",
      "routeId": "19614",
      "tripId": "3358662",
      "lat": 38.732940673828125,
      "lon": -90.39067840576172,
      "bearingDeg": 0,
      "speedMps": 0,
      "timestamp": 1779119728,
      "mode": "bus"
    },
    {
      "id": "6835",
      "label": "32 Dr ML King - WEST",
      "routeId": "19607",
      "tripId": "3357817",
      "lat": 38.630210876464844,
      "lon": -90.20018768310547,
      "bearingDeg": 0,
      "speedMps": 0,
      "timestamp": 1779119727,
      "mode": "bus"
    },
    {
      "id": "6837",
      "label": "97 Delmar - EAST",
      "routeId": "19633",
      "tripId": "3361777",
      "lat": 38.65296936035156,
      "lon": -90.27442169189453,
      "bearingDeg": 0,
      "speedMps": 0,
      "timestamp": 1779119733,
      "mode": "bus"
    },
    {
      "id": "6838",
      "label": "4 Natural Bridge - EAST",
      "routeId": "19594",
      "tripId": "3356092",
      "lat": 38.70515823364258,
      "lon": -90.3052978515625,
      "bearingDeg": 0,
      "speedMps": 0,
      "timestamp": 1779119743,
      "mode": "bus"
    },
    {
      "id": "6840",
      "label": "73 Carondelet - SOUTH",
      "routeId": "19623",
      "tripId": "3360035",
      "lat": 38.613258361816406,
      "lon": -90.20578002929688,
      "bearingDeg": 0,
      "speedMps": 0,
      "timestamp": 1779119749,
      "mode": "bus"
    },
    {
      "id": "6841",
      "label": "74 Florissant - SOUTH",
      "routeId": "19624",
      "tripId": "3360263",
      "lat": 38.76670837402344,
      "lon": -90.28069305419922,
      "bearingDeg": 0,
      "speedMps": 0,
      "timestamp": 1779119740,
      "mode": "bus"
    },
    {
      "id": "6842",
      "label": "31 Chouteau - EAST",
      "routeId": "19606",
      "tripId": "3357692",
      "lat": 38.62445831298828,
      "lon": -90.22944641113281,
      "bearingDeg": 0,
      "speedMps": 0,
      "timestamp": 1779119745,
      "mode": "bus"
    },
    {
      "id": "6846",
      "label": "74 Florissant - SOUTH",
      "routeId": "19624",
      "tripId": "3360262",
      "lat": 38.63447189331055,
      "lon": -90.19819641113281,
      "bearingDeg": 0,
      "speedMps": 0,
      "timestamp": 1779119729,
      "mode": "bus"
    },
    {
      "id": "6853",
      "label": "1 Main Street - State Street - WEST",
      "routeId": "19636",
      "tripId": "3362194",
      "lat": 38.595741271972656,
      "lon": -90.04875946044922,
      "bearingDeg": 0,
      "speedMps": 0,
      "timestamp": 1779119741,
      "mode": "bus"
    },
    {
      "id": "6902",
      "label": "10 Gravois-Lindell - SOUTH",
      "routeId": "19598",
      "tripId": "3356514",
      "lat": 38.584991455078125,
      "lon": -90.26252746582031,
      "bearingDeg": 0,
      "speedMps": 0,
      "timestamp": 1779119725,
      "mode": "bus"
    },
    {
      "id": "6903",
      "label": "10 Gravois-Lindell - SOUTH",
      "routeId": "19598",
      "tripId": "3356548",
      "lat": 38.641231536865234,
      "lon": -90.26522827148438,
      "bearingDeg": 0,
      "speedMps": 0,
      "timestamp": 1779119749,
      "mode": "bus"
    },
    {
      "id": "6904",
      "label": "95 Kingshighway - SOUTH",
      "routeId": "19632",
      "tripId": "3361576",
      "lat": 38.582401275634766,
      "lon": -90.27812194824219,
      "bearingDeg": 0,
      "speedMps": 0,
      "timestamp": 1779119691,
      "mode": "bus"
    },
    {
      "id": "6909",
      "label": "10 Gravois-Lindell - NORTH",
      "routeId": "19598",
      "tripId": "3356456",
      "lat": 38.6319694519043,
      "lon": -90.2081069946289,
      "bearingDeg": 0,
      "speedMps": 0,
      "timestamp": 1779119723,
      "mode": "bus"
    },
    {
      "id": "6911",
      "label": "73 Carondelet - NORTH",
      "routeId": "19623",
      "tripId": "3360082",
      "lat": 38.54618835449219,
      "lon": -90.2696533203125,
      "bearingDeg": 0,
      "speedMps": 0,
      "timestamp": 1779119743,
      "mode": "bus"
    },
    {
      "id": "6913",
      "label": "95 Kingshighway - SOUTH",
      "routeId": "19632",
      "tripId": "3361577",
      "lat": 38.63301086425781,
      "lon": -90.26058197021484,
      "bearingDeg": 0,
      "speedMps": 0,
      "timestamp": 1779119722,
      "mode": "bus"
    },
    {
      "id": "6914",
      "label": "30 Arsenal - WEST",
      "routeId": "19605",
      "tripId": "3357611",
      "lat": 38.60708999633789,
      "lon": -90.28939819335938,
      "bearingDeg": 0,
      "speedMps": 0,
      "timestamp": 1779119741,
      "mode": "bus"
    },
    {
      "id": "6916",
      "label": "74 Florissant - NORTH",
      "routeId": "19624",
      "tripId": "3360311",
      "lat": 38.66896057128906,
      "lon": -90.21077728271484,
      "bearingDeg": 0,
      "speedMps": 0,
      "timestamp": 1779119746,
      "mode": "bus"
    },
    {
      "id": "6918",
      "label": "64 Lucas-Hunt - NORTH",
      "routeId": "19621",
      "tripId": "3359497",
      "lat": 38.734378814697266,
      "lon": -90.26502990722656,
      "bearingDeg": 0,
      "speedMps": 0,
      "timestamp": 1779119731,
      "mode": "bus"
    },
    {
      "id": "6924",
      "label": "35 Rock Road - WEST",
      "routeId": "19610",
      "tripId": "3358132",
      "lat": 38.69245910644531,
      "lon": -90.31627655029297,
      "bearingDeg": 0,
      "speedMps": 0,
      "timestamp": 1779119744,
      "mode": "bus"
    },
    {
      "id": "6925",
      "label": "94 Page - EAST",
      "routeId": "19631",
      "tripId": "3361344",
      "lat": 38.64564895629883,
      "lon": -90.22689056396484,
      "bearingDeg": 0,
      "speedMps": 0,
      "timestamp": 1779119744,
      "mode": "bus"
    },
    {
      "id": "6927",
      "label": "74 Florissant - SOUTH",
      "routeId": "19624",
      "tripId": "3360241",
      "lat": 38.70697021484375,
      "lon": -90.24970245361328,
      "bearingDeg": 0,
      "speedMps": 0,
      "timestamp": 1779119735,
      "mode": "bus"
    },
    {
      "id": "6932",
      "label": "90 Hampton - NORTH",
      "routeId": "19629",
      "tripId": "3361029",
      "lat": 38.653560638427734,
      "lon": -90.28439331054688,
      "bearingDeg": 0,
      "speedMps": 0,
      "timestamp": 1779119731,
      "mode": "bus"
    },
    {
      "id": "6935",
      "label": "79 Ferguson-Clayton - SOUTH",
      "routeId": "19628",
      "tripId": "3360879",
      "lat": 38.77315902709961,
      "lon": -90.30796813964844,
      "bearingDeg": 0,
      "speedMps": 0,
      "timestamp": 1779119738,
      "mode": "bus"
    },
    {
      "id": "6937",
      "label": "74 Florissant - NORTH",
      "routeId": "19624",
      "tripId": "3360290",
      "lat": 38.71757125854492,
      "lon": -90.26106262207031,
      "bearingDeg": 0,
      "speedMps": 0,
      "timestamp": 1779119696,
      "mode": "bus"
    },
    {
      "id": "6938",
      "label": "4 Natural Bridge - WEST",
      "routeId": "19594",
      "tripId": "3356146",
      "lat": 38.63056182861328,
      "lon": -90.2123031616211,
      "bearingDeg": 0,
      "speedMps": 0,
      "timestamp": 1779119748,
      "mode": "bus"
    },
    {
      "id": "6940",
      "label": "74 Florissant - SOUTH",
      "routeId": "19624",
      "tripId": "3360240",
      "lat": 38.642311096191406,
      "lon": -90.19599914550781,
      "bearingDeg": 0,
      "speedMps": 0,
      "timestamp": 1779119732,
      "mode": "bus"
    },
    {
      "id": "6943",
      "label": "41 Lee - SOUTH",
      "routeId": "19612",
      "tripId": "3358402",
      "lat": 38.640079498291016,
      "lon": -90.2057113647461,
      "bearingDeg": 0,
      "speedMps": 0,
      "timestamp": 1779119744,
      "mode": "bus"
    },
    {
      "id": "6951",
      "label": "12 OFallon-Fairview Heights - EAST",
      "routeId": "19644",
      "tripId": "3363436",
      "lat": 38.592891693115234,
      "lon": -89.99735260009766,
      "bearingDeg": 0,
      "speedMps": 0,
      "timestamp": 1779119725,
      "mode": "bus"
    },
    {
      "id": "6953",
      "label": "1 Main Street - State Street - WEST",
      "routeId": "19636",
      "tripId": "3362195",
      "lat": 38.53300094604492,
      "lon": -90.0154037475586,
      "bearingDeg": 0,
      "speedMps": 0,
      "timestamp": 1779119729,
      "mode": "bus"
    },
    {
      "id": "6954",
      "label": "1 Main Street - State Street - EAST",
      "routeId": "19636",
      "tripId": "3362249",
      "lat": 38.6226692199707,
      "lon": -90.14533996582031,
      "bearingDeg": 0,
      "speedMps": 0,
      "timestamp": 1779119733,
      "mode": "bus"
    },
    {
      "id": "7001",
      "label": "70 Grand - NORTH",
      "routeId": "19622",
      "tripId": "3359740",
      "lat": 38.60948181152344,
      "lon": -90.24076843261719,
      "bearingDeg": 0,
      "speedMps": 0,
      "timestamp": 1779119720,
      "mode": "bus"
    },
    {
      "id": "7002",
      "label": "95 Kingshighway - NORTH",
      "routeId": "19632",
      "tripId": "3361622",
      "lat": 38.68251037597656,
      "lon": -90.22633361816406,
      "bearingDeg": 0,
      "speedMps": 0,
      "timestamp": 1779119737,
      "mode": "bus"
    },
    {
      "id": "7004",
      "label": "70 Grand - NORTH",
      "routeId": "19622",
      "tripId": "3359741",
      "lat": 38.59001922607422,
      "lon": -90.24417114257812,
      "bearingDeg": 0,
      "speedMps": 0,
      "timestamp": 1779119731,
      "mode": "bus"
    },
    {
      "id": "7006",
      "label": "70 Grand - NORTH",
      "routeId": "19622",
      "tripId": "3359737",
      "lat": 38.685081481933594,
      "lon": -90.2188491821289,
      "bearingDeg": 0,
      "speedMps": 0,
      "timestamp": 1779119739,
      "mode": "bus"
    },
    {
      "id": "7007",
      "label": "21 Watson Rd - EAST",
      "routeId": "19604",
      "tripId": "3365090",
      "lat": 38.555381774902344,
      "lon": -90.40757751464844,
      "bearingDeg": 0,
      "speedMps": 0,
      "timestamp": 1779119737,
      "mode": "bus"
    },
    {
      "id": "7012",
      "label": "98 Ballas-North Hanley - SOUTH",
      "routeId": "19634",
      "tripId": "3361892",
      "lat": 38.723060607910156,
      "lon": -90.3227767944336,
      "bearingDeg": 0,
      "speedMps": 0,
      "timestamp": 1779119726,
      "mode": "bus"
    },
    {
      "id": "7013",
      "label": "73 Carondelet - NORTH",
      "routeId": "19623",
      "tripId": "3360081",
      "lat": 38.59661102294922,
      "lon": -90.20948028564453,
      "bearingDeg": 0,
      "speedMps": 0,
      "timestamp": 1779119750,
      "mode": "bus"
    },
    {
      "id": "7014",
      "label": "70 Grand - SOUTH",
      "routeId": "19622",
      "tripId": "3359658",
      "lat": 38.66231918334961,
      "lon": -90.21604919433594,
      "bearingDeg": 0,
      "speedMps": 0,
      "timestamp": 1779119739,
      "mode": "bus"
    },
    {
      "id": "7016",
      "label": "4 Natural Bridge - WEST",
      "routeId": "19594",
      "tripId": "3356145",
      "lat": 38.69738006591797,
      "lon": -90.28733825683594,
      "bearingDeg": 0,
      "speedMps": 0,
      "timestamp": 1779119751,
      "mode": "bus"
    },
    {
      "id": "7017",
      "label": "40 Broadway-Halls Ferry - SOUTH",
      "routeId": "19611",
      "tripId": "3358305",
      "lat": 38.710079193115234,
      "lon": -90.23040771484375,
      "bearingDeg": 0,
      "speedMps": 0,
      "timestamp": 1779119752,
      "mode": "bus"
    },
    {
      "id": "7022",
      "label": "77 Village Square - NORTH",
      "routeId": "19626",
      "tripId": "3360635",
      "lat": 38.74673080444336,
      "lon": -90.33477020263672,
      "bearingDeg": 0,
      "speedMps": 0,
      "timestamp": 1779119748,
      "mode": "bus"
    },
    {
      "id": "7023",
      "label": "41 Lee - NORTH",
      "routeId": "19612",
      "tripId": "3358423",
      "lat": 38.6897087097168,
      "lon": -90.24732971191406,
      "bearingDeg": 0,
      "speedMps": 0,
      "timestamp": 1779119736,
      "mode": "bus"
    },
    {
      "id": "7024",
      "label": "97 Delmar - WEST",
      "routeId": "19633",
      "tripId": "3361797",
      "lat": 38.655311584472656,
      "lon": -90.2960205078125,
      "bearingDeg": 0,
      "speedMps": 0,
      "timestamp": 1779119736,
      "mode": "bus"
    },
    {
      "id": "7025",
      "label": "78 Bellefontaine - SOUTH",
      "routeId": "19627",
      "tripId": "3360773",
      "lat": 38.79307174682617,
      "lon": -90.28749084472656,
      "bearingDeg": 0,
      "speedMps": 0,
      "timestamp": 1779119740,
      "mode": "bus"
    },
    {
      "id": "7103",
      "label": "70 Grand - SOUTH",
      "routeId": "19622",
      "tripId": "3359655",
      "lat": 38.57688903808594,
      "lon": -90.24738311767578,
      "bearingDeg": 0,
      "speedMps": 0,
      "timestamp": 1779119749,
      "mode": "bus"
    },
    {
      "id": "7107",
      "label": "34 Earth City - COUNTERCLOCKWIS",
      "routeId": "19609",
      "tripId": "3358028",
      "lat": 38.725990295410156,
      "lon": -90.32653045654297,
      "bearingDeg": 0,
      "speedMps": 0,
      "timestamp": 1779119746,
      "mode": "bus"
    },
    {
      "id": "7115",
      "label": "100 Hazelwood - WEST",
      "routeId": "19635",
      "tripId": "3362020",
      "lat": 38.72605895996094,
      "lon": -90.31846618652344,
      "bearingDeg": 0,
      "speedMps": 0,
      "timestamp": 1779119731,
      "mode": "bus"
    },
    {
      "id": "7119",
      "label": "64 Lucas-Hunt - SOUTH",
      "routeId": "19621",
      "tripId": "3359468",
      "lat": 38.684791564941406,
      "lon": -90.30171203613281,
      "bearingDeg": 0,
      "speedMps": 0,
      "timestamp": 1779119744,
      "mode": "bus"
    },
    {
      "id": "7120",
      "label": "4 Natural Bridge - EAST",
      "routeId": "19594",
      "tripId": "3356091",
      "lat": 38.651519775390625,
      "lon": -90.21163940429688,
      "bearingDeg": 0,
      "speedMps": 0,
      "timestamp": 1779119741,
      "mode": "bus"
    },
    {
      "id": "7121",
      "label": "77 Village Square - SOUTH",
      "routeId": "19626",
      "tripId": "3360603",
      "lat": 38.79505920410156,
      "lon": -90.34081268310547,
      "bearingDeg": 0,
      "speedMps": 0,
      "timestamp": 1779119723,
      "mode": "bus"
    },
    {
      "id": "7124",
      "label": "61 Chambers Rd - WEST",
      "routeId": "19620",
      "tripId": "3359292",
      "lat": 38.74869155883789,
      "lon": -90.30661010742188,
      "bearingDeg": 0,
      "speedMps": 0,
      "timestamp": 1779119710,
      "mode": "bus"
    },
    {
      "id": "7151",
      "label": "1 Main Street - State Street - WEST",
      "routeId": "19636",
      "tripId": "3362193",
      "lat": 38.615989685058594,
      "lon": -90.12682342529297,
      "bearingDeg": 0,
      "speedMps": 0,
      "timestamp": 1779119726,
      "mode": "bus"
    },
    {
      "id": "7152",
      "label": "12 OFallon-Fairview Heights - EAST",
      "routeId": "19644",
      "tripId": "3363435",
      "lat": 38.59247970581055,
      "lon": -89.94921112060547,
      "bearingDeg": 0,
      "speedMps": 0,
      "timestamp": 1779119714,
      "mode": "bus"
    },
    {
      "id": "7154",
      "label": "1 Main Street - State Street - EAST",
      "routeId": "19636",
      "tripId": "3362247",
      "lat": 38.54096984863281,
      "lon": -90.02420043945312,
      "bearingDeg": 0,
      "speedMps": 0,
      "timestamp": 1779119730,
      "mode": "bus"
    },
    {
      "id": "7201",
      "label": "73 Carondelet - SOUTH",
      "routeId": "19623",
      "tripId": "3360034",
      "lat": 38.57176971435547,
      "lon": -90.24385833740234,
      "bearingDeg": 0,
      "speedMps": 0,
      "timestamp": 1779119735,
      "mode": "bus"
    },
    {
      "id": "7203",
      "label": "11 Chippewa - EAST",
      "routeId": "19599",
      "tripId": "3356700",
      "lat": 38.61970901489258,
      "lon": -90.21952819824219,
      "bearingDeg": 0,
      "speedMps": 0,
      "timestamp": 1779119725,
      "mode": "bus"
    },
    {
      "id": "7205",
      "label": "95 Kingshighway - NORTH",
      "routeId": "19632",
      "tripId": "3361624",
      "lat": 38.61643981933594,
      "lon": -90.26679229736328,
      "bearingDeg": 0,
      "speedMps": 0,
      "timestamp": 1779119749,
      "mode": "bus"
    },
    {
      "id": "7206",
      "label": "95 Kingshighway - SOUTH",
      "routeId": "19632",
      "tripId": "3361578",
      "lat": 38.664588928222656,
      "lon": -90.26056671142578,
      "bearingDeg": 0,
      "speedMps": 0,
      "timestamp": 1779119732,
      "mode": "bus"
    },
    {
      "id": "7209",
      "label": "31 Chouteau - WEST",
      "routeId": "19606",
      "tripId": "3357714",
      "lat": 38.61272048950195,
      "lon": -90.32454681396484,
      "bearingDeg": 0,
      "speedMps": 0,
      "timestamp": 1779119741,
      "mode": "bus"
    },
    {
      "id": "7212",
      "label": "91 Olive - WEST",
      "routeId": "19630",
      "tripId": "3361230",
      "lat": 38.68074035644531,
      "lon": -90.47457122802734,
      "bearingDeg": 0,
      "speedMps": 0,
      "timestamp": 1779119726,
      "mode": "bus"
    },
    {
      "id": "7213",
      "label": "77 Village Square - NORTH",
      "routeId": "19626",
      "tripId": "3360634",
      "lat": 38.777889251708984,
      "lon": -90.28109741210938,
      "bearingDeg": 0,
      "speedMps": 0,
      "timestamp": 1779119722,
      "mode": "bus"
    },
    {
      "id": "7216",
      "label": "32 Dr ML King - EAST",
      "routeId": "19607",
      "tripId": "3357842",
      "lat": 38.640499114990234,
      "lon": -90.19140625,
      "bearingDeg": 0,
      "speedMps": 0,
      "timestamp": 1779119750,
      "mode": "bus"
    },
    {
      "id": "7217",
      "label": "61 Chambers Rd - WEST",
      "routeId": "19620",
      "tripId": "3359293",
      "lat": 38.7275505065918,
      "lon": -90.22386169433594,
      "bearingDeg": 0,
      "speedMps": 0,
      "timestamp": 1779119738,
      "mode": "bus"
    },
    {
      "id": "7301",
      "label": "8 Shaw-Cherokee - NORTH",
      "routeId": "19596",
      "tripId": "3356325",
      "lat": 38.60142135620117,
      "lon": -90.24240112304688,
      "bearingDeg": 0,
      "speedMps": 0,
      "timestamp": 1779119710,
      "mode": "bus"
    },
    {
      "id": "7303",
      "label": "8 Shaw-Cherokee - SOUTH",
      "routeId": "19596",
      "tripId": "3356299",
      "lat": 38.62828063964844,
      "lon": -90.2564468383789,
      "bearingDeg": 0,
      "speedMps": 0,
      "timestamp": 1779119745,
      "mode": "bus"
    },
    {
      "id": "7305",
      "label": "59 Oakland - WEST",
      "routeId": "19618",
      "tripId": "3359012",
      "lat": 38.63235855102539,
      "lon": -90.26640319824219,
      "bearingDeg": 0,
      "speedMps": 0,
      "timestamp": 1779119727,
      "mode": "bus"
    },
    {
      "id": "7310",
      "label": "5 Green - CLOCKWISE",
      "routeId": "19595",
      "tripId": "3356271",
      "lat": 38.65776062011719,
      "lon": -90.3084487915039,
      "bearingDeg": 0,
      "speedMps": 0,
      "timestamp": 1779119717,
      "mode": "bus"
    },
    {
      "id": "7312",
      "label": "2 Red - NORTH",
      "routeId": "19593",
      "tripId": "3355988",
      "lat": 38.62628173828125,
      "lon": -90.34652709960938,
      "bearingDeg": 0,
      "speedMps": 0,
      "timestamp": 1779119729,
      "mode": "rail"
    },
    {
      "id": "7319",
      "label": "2 Red - SOUTH",
      "routeId": "19593",
      "tripId": "3355959",
      "lat": 38.656410217285156,
      "lon": -90.29750061035156,
      "bearingDeg": 0,
      "speedMps": 0,
      "timestamp": 1779119746,
      "mode": "rail"
    },
    {
      "id": "7502",
      "label": "42 Sarah - NORTH",
      "routeId": "19613",
      "tripId": "3358545",
      "lat": 38.646480560302734,
      "lon": -90.24162292480469,
      "bearingDeg": 0,
      "speedMps": 0,
      "timestamp": 1779119753,
      "mode": "bus"
    },
    {
      "id": "7503",
      "label": "60 Shepley-Lilac - NORTH",
      "routeId": "19619",
      "tripId": "3359091",
      "lat": 38.76594161987305,
      "lon": -90.23885345458984,
      "bearingDeg": 0,
      "speedMps": 0,
      "timestamp": 1779119753,
      "mode": "bus"
    },
    {
      "id": "7510",
      "label": "13 Union - NORTH",
      "routeId": "19600",
      "tripId": "3356959",
      "lat": 38.63811111450195,
      "lon": -90.25930786132812,
      "bearingDeg": 0,
      "speedMps": 0,
      "timestamp": 1779119750,
      "mode": "bus"
    },
    {
      "id": "7513",
      "label": "60 Shepley-Lilac - SOUTH",
      "routeId": "19619",
      "tripId": "3359119",
      "lat": 38.7315788269043,
      "lon": -90.2277603149414,
      "bearingDeg": 0,
      "speedMps": 0,
      "timestamp": 1779119740,
      "mode": "bus"
    },
    {
      "id": "7515",
      "label": "18 Taylor - NORTH",
      "routeId": "19602",
      "tripId": "3357206",
      "lat": 38.66168975830078,
      "lon": -90.24523162841797,
      "bearingDeg": 0,
      "speedMps": 0,
      "timestamp": 1779119751,
      "mode": "bus"
    },
    {
      "id": "7555",
      "label": "14 Memorial Hosp-Westfield Plaza - EAST",
      "routeId": "19646",
      "tripId": "3363757",
      "lat": 38.555198669433594,
      "lon": -90.02005767822266,
      "bearingDeg": 0,
      "speedMps": 0,
      "timestamp": 1779119658,
      "mode": "bus"
    },
    {
      "id": "7561",
      "label": "13 Caseyville - NORTH",
      "routeId": "19645",
      "tripId": "3363662",
      "lat": 38.65705108642578,
      "lon": -89.98660278320312,
      "bearingDeg": 0,
      "speedMps": 0,
      "timestamp": 1779119748,
      "mode": "bus"
    },
    {
      "id": "7562",
      "label": "4 19th & Central - CLOCKWISE",
      "routeId": "19639",
      "tripId": "3362733",
      "lat": 38.61476135253906,
      "lon": -90.15853881835938,
      "bearingDeg": 0,
      "speedMps": 0,
      "timestamp": 1779119731,
      "mode": "bus"
    },
    {
      "id": "7563",
      "label": "2 Cahokia Heights - SOUTH",
      "routeId": "19637",
      "tripId": "3362498",
      "lat": 38.619049072265625,
      "lon": -90.16201782226562,
      "bearingDeg": 0,
      "speedMps": 0,
      "timestamp": 1779119726,
      "mode": "bus"
    },
    {
      "id": "7565",
      "label": "23 Belleville-College - WEST",
      "routeId": "19649",
      "tripId": "3364059",
      "lat": 38.5195198059082,
      "lon": -89.92781829833984,
      "bearingDeg": 0,
      "speedMps": 0,
      "timestamp": 1779119749,
      "mode": "bus"
    },
    {
      "id": "7573",
      "label": "16 St. Clair Square - SOUTH",
      "routeId": "19648",
      "tripId": "3363900",
      "lat": 38.59640121459961,
      "lon": -89.98381042480469,
      "bearingDeg": 0,
      "speedMps": 0,
      "timestamp": 1779119702,
      "mode": "bus"
    },
    {
      "id": "7574",
      "label": "8 Alta Sita - NORTH",
      "routeId": "19642",
      "tripId": "3363124",
      "lat": 38.63056945800781,
      "lon": -90.1409683227539,
      "bearingDeg": 0,
      "speedMps": 0,
      "timestamp": 1779119750,
      "mode": "bus"
    },
    {
      "id": "7577",
      "label": "8 Alta Sita - SOUTH",
      "routeId": "19642",
      "tripId": "3363104",
      "lat": 38.549888610839844,
      "lon": -90.13027954101562,
      "bearingDeg": 0,
      "speedMps": 0,
      "timestamp": 1779119694,
      "mode": "bus"
    },
    {
      "id": "7603",
      "label": "90 Hampton - SOUTH",
      "routeId": "19629",
      "tripId": "3361064",
      "lat": 38.61574935913086,
      "lon": -90.28730010986328,
      "bearingDeg": 0,
      "speedMps": 0,
      "timestamp": 1779119747,
      "mode": "bus"
    },
    {
      "id": "7606",
      "label": "61 Chambers Rd - EAST",
      "routeId": "19620",
      "tripId": "3359243",
      "lat": 38.733131408691406,
      "lon": -90.22737121582031,
      "bearingDeg": 0,
      "speedMps": 0,
      "timestamp": 1779119724,
      "mode": "bus"
    },
    {
      "id": "7608",
      "label": "78 Bellefontaine - NORTH",
      "routeId": "19627",
      "tripId": "3360744",
      "lat": 38.769989013671875,
      "lon": -90.27880096435547,
      "bearingDeg": 0,
      "speedMps": 0,
      "timestamp": 1779119712,
      "mode": "bus"
    },
    {
      "id": "7609",
      "label": "61 Chambers Rd - EAST",
      "routeId": "19620",
      "tripId": "3359262",
      "lat": 38.74776077270508,
      "lon": -90.31697845458984,
      "bearingDeg": 0,
      "speedMps": 0,
      "timestamp": 1779119725,
      "mode": "bus"
    },
    {
      "id": "7612",
      "label": "90 Hampton - SOUTH",
      "routeId": "19629",
      "tripId": "3361065",
      "lat": 38.67858123779297,
      "lon": -90.2750473022461,
      "bearingDeg": 0,
      "speedMps": 0,
      "timestamp": 1779119739,
      "mode": "bus"
    },
    {
      "id": "7652",
      "label": "15 Belleville-O'Fallon - WEST",
      "routeId": "19647",
      "tripId": "3363785",
      "lat": 38.53644943237305,
      "lon": -89.96218872070312,
      "bearingDeg": 0,
      "speedMps": 0,
      "timestamp": 1779119736,
      "mode": "bus"
    },
    {
      "id": "7654",
      "label": "8 Alta Sita - SOUTH",
      "routeId": "19642",
      "tripId": "3363077",
      "lat": 38.622398376464844,
      "lon": -90.12625885009766,
      "bearingDeg": 0,
      "speedMps": 0,
      "timestamp": 1779119638,
      "mode": "bus"
    },
    {
      "id": "7655",
      "label": "9 Washington Park - WEST",
      "routeId": "19643",
      "tripId": "3363311",
      "lat": 38.615638732910156,
      "lon": -90.09278869628906,
      "bearingDeg": 0,
      "speedMps": 0,
      "timestamp": 1779119734,
      "mode": "bus"
    },
    {
      "id": "7656",
      "label": "16 St. Clair Square - NORTH",
      "routeId": "19648",
      "tripId": "3363833",
      "lat": 38.51559066772461,
      "lon": -89.97908782958984,
      "bearingDeg": 0,
      "speedMps": 0,
      "timestamp": 1779119664,
      "mode": "bus"
    },
    {
      "id": "7658",
      "label": "8 Alta Sita - NORTH",
      "routeId": "19642",
      "tripId": "3363151",
      "lat": 38.569671630859375,
      "lon": -90.10574340820312,
      "bearingDeg": 0,
      "speedMps": 0,
      "timestamp": 1779119745,
      "mode": "bus"
    },
    {
      "id": "7659",
      "label": "3 Sauget - Water Street - NORTH",
      "routeId": "19638",
      "tripId": "3362646",
      "lat": 38.55023956298828,
      "lon": -90.201171875,
      "bearingDeg": 0,
      "speedMps": 0,
      "timestamp": 1779119750,
      "mode": "bus"
    },
    {
      "id": "7753",
      "label": "1 Main Street - State Street - EAST",
      "routeId": "19636",
      "tripId": "3362248",
      "lat": 38.58937072753906,
      "lon": -90.06159210205078,
      "bearingDeg": 0,
      "speedMps": 0,
      "timestamp": 1779119731,
      "mode": "bus"
    },
    {
      "id": "7756",
      "label": "12 OFallon-Fairview Heights - WEST",
      "routeId": "19644",
      "tripId": "3363483",
      "lat": 38.60005187988281,
      "lon": -89.98493194580078,
      "bearingDeg": 0,
      "speedMps": 0,
      "timestamp": 1779119736,
      "mode": "bus"
    }
  ]
}
