{
  "updatedAt": "2026-05-22T01:51:30.108Z",
  "source": "Metro St. Louis GTFS-Realtime vehicles",
  "vehicles": [
    {
      "id": "3831",
      "label": "57 Manchester - EAST",
      "routeId": "19616",
      "tripId": "3358807",
      "lat": 38.60285186767578,
      "lon": -90.44026947021484,
      "bearingDeg": 0,
      "speedMps": 0,
      "timestamp": 1779414644,
      "mode": "bus"
    },
    {
      "id": "3834",
      "label": "70 Grand - NORTH",
      "routeId": "19622",
      "tripId": "3359785",
      "lat": 38.60260009765625,
      "lon": -90.24224853515625,
      "bearingDeg": 0,
      "speedMps": 0,
      "timestamp": 1779414649,
      "mode": "bus"
    },
    {
      "id": "3843",
      "label": "58 Chesterfield Valley - WEST",
      "routeId": "19617",
      "tripId": "3358941",
      "lat": 38.63898849487305,
      "lon": -90.4418716430664,
      "bearingDeg": 0,
      "speedMps": 0,
      "timestamp": 1779414621,
      "mode": "bus"
    },
    {
      "id": "3848",
      "label": "95 Kingshighway - NORTH",
      "routeId": "19632",
      "tripId": "3361610",
      "lat": 38.662750244140625,
      "lon": -90.26155853271484,
      "bearingDeg": 0,
      "speedMps": 0,
      "timestamp": 1779414647,
      "mode": "bus"
    },
    {
      "id": "3849",
      "label": "49 Lindbergh - SOUTH",
      "routeId": "19614",
      "tripId": "3358636",
      "lat": 38.563011169433594,
      "lon": -90.406982421875,
      "bearingDeg": 0,
      "speedMps": 0,
      "timestamp": 1779414629,
      "mode": "bus"
    },
    {
      "id": "3850",
      "label": "16 City Limits - SOUTH",
      "routeId": "19601",
      "tripId": "3365214",
      "lat": 38.68622970581055,
      "lon": -90.27998352050781,
      "bearingDeg": 0,
      "speedMps": 0,
      "timestamp": 1779414632,
      "mode": "bus"
    },
    {
      "id": "3852",
      "label": "16 City Limits - NORTH",
      "routeId": "19601",
      "tripId": "3365243",
      "lat": 38.655391693115234,
      "lon": -90.29943084716797,
      "bearingDeg": 0,
      "speedMps": 0,
      "timestamp": 1779414629,
      "mode": "bus"
    },
    {
      "id": "3856",
      "label": "49 Lindbergh - NORTH",
      "routeId": "19614",
      "tripId": "3358660",
      "lat": 38.50508117675781,
      "lon": -90.33332824707031,
      "bearingDeg": 0,
      "speedMps": 0,
      "timestamp": 1779414635,
      "mode": "bus"
    },
    {
      "id": "3857",
      "label": "73 Carondelet - SOUTH",
      "routeId": "19623",
      "tripId": "3360015",
      "lat": 38.55236053466797,
      "lon": -90.25747680664062,
      "bearingDeg": 0,
      "speedMps": 0,
      "timestamp": 1779414646,
      "mode": "bus"
    },
    {
      "id": "3858",
      "label": "95 Kingshighway - SOUTH",
      "routeId": "19632",
      "tripId": "3361554",
      "lat": 38.689491271972656,
      "lon": -90.23446655273438,
      "bearingDeg": 0,
      "speedMps": 0,
      "timestamp": 1779414609,
      "mode": "bus"
    },
    {
      "id": "6607",
      "label": "90 Hampton - SOUTH",
      "routeId": "19629",
      "tripId": "3361075",
      "lat": 38.65127944946289,
      "lon": -90.28484344482422,
      "bearingDeg": 0,
      "speedMps": 0,
      "timestamp": 1779414640,
      "mode": "bus"
    },
    {
      "id": "6608",
      "label": "94 Page - WEST",
      "routeId": "19631",
      "tripId": "3361373",
      "lat": 38.66069030761719,
      "lon": -90.26937103271484,
      "bearingDeg": 0,
      "speedMps": 0,
      "timestamp": 1779414649,
      "mode": "bus"
    },
    {
      "id": "6619",
      "label": "74 Florissant - SOUTH",
      "routeId": "19624",
      "tripId": "3360220",
      "lat": 38.76350021362305,
      "lon": -90.2801513671875,
      "bearingDeg": 0,
      "speedMps": 0,
      "timestamp": 1779414632,
      "mode": "bus"
    },
    {
      "id": "6701",
      "label": "12 OFallon-Fairview Heights - EAST",
      "routeId": "19644",
      "tripId": "3363461",
      "lat": 38.58477020263672,
      "lon": -89.90738677978516,
      "bearingDeg": 0,
      "speedMps": 0,
      "timestamp": 1779414623,
      "mode": "bus"
    },
    {
      "id": "6704",
      "label": "21 Watson Rd - WEST",
      "routeId": "19604",
      "tripId": "3365116",
      "lat": 38.566871643066406,
      "lon": -90.41224670410156,
      "bearingDeg": 0,
      "speedMps": 0,
      "timestamp": 1779414648,
      "mode": "bus"
    },
    {
      "id": "6705",
      "label": "19 St Louis Ave - WEST",
      "routeId": "19603",
      "tripId": "3357302",
      "lat": 38.67734146118164,
      "lon": -90.26776885986328,
      "bearingDeg": 0,
      "speedMps": 0,
      "timestamp": 1779414636,
      "mode": "bus"
    },
    {
      "id": "6712",
      "label": "8 Shaw-Cherokee - NORTH",
      "routeId": "19596",
      "tripId": "3356315",
      "lat": 38.552391052246094,
      "lon": -90.25225067138672,
      "bearingDeg": 0,
      "speedMps": 0,
      "timestamp": 1779414626,
      "mode": "bus"
    },
    {
      "id": "6716",
      "label": "11 Chippewa - EAST",
      "routeId": "19599",
      "tripId": "3356675",
      "lat": 38.588138580322266,
      "lon": -90.24336242675781,
      "bearingDeg": 0,
      "speedMps": 0,
      "timestamp": 1779414616,
      "mode": "bus"
    },
    {
      "id": "6729",
      "label": "21 Watson Rd - EAST",
      "routeId": "19604",
      "tripId": "3365099",
      "lat": 38.574039459228516,
      "lon": -90.33194732666016,
      "bearingDeg": 0,
      "speedMps": 0,
      "timestamp": 1779414649,
      "mode": "bus"
    },
    {
      "id": "6741",
      "label": "10 Gravois-Lindell - SOUTH",
      "routeId": "19598",
      "tripId": "3356534",
      "lat": 38.60367965698242,
      "lon": -90.2260513305664,
      "bearingDeg": 0,
      "speedMps": 0,
      "timestamp": 1779414632,
      "mode": "bus"
    },
    {
      "id": "6752",
      "label": "12 OFallon-Fairview Heights - WEST",
      "routeId": "19644",
      "tripId": "3363510",
      "lat": 38.592681884765625,
      "lon": -89.95124053955078,
      "bearingDeg": 0,
      "speedMps": 0,
      "timestamp": 1779414587,
      "mode": "bus"
    },
    {
      "id": "6755",
      "label": "1 Main Street - State Street - EAST",
      "routeId": "19636",
      "tripId": "3362223",
      "lat": 38.56373977661133,
      "lon": -90.0482406616211,
      "bearingDeg": 0,
      "speedMps": 0,
      "timestamp": 1779414622,
      "mode": "bus"
    },
    {
      "id": "6809",
      "label": "94 Page - EAST",
      "routeId": "19631",
      "tripId": "3361333",
      "lat": 38.69224166870117,
      "lon": -90.39732360839844,
      "bearingDeg": 0,
      "speedMps": 0,
      "timestamp": 1779414641,
      "mode": "bus"
    },
    {
      "id": "6810",
      "label": "94 Page - EAST",
      "routeId": "19631",
      "tripId": "3361332",
      "lat": 38.65087890625,
      "lon": -90.23883819580078,
      "bearingDeg": 0,
      "speedMps": 0,
      "timestamp": 1779414634,
      "mode": "bus"
    },
    {
      "id": "6811",
      "label": "90 Hampton - NORTH",
      "routeId": "19629",
      "tripId": "3361036",
      "lat": 38.72241973876953,
      "lon": -90.24078369140625,
      "bearingDeg": 0,
      "speedMps": 0,
      "timestamp": 1779414593,
      "mode": "bus"
    },
    {
      "id": "6812",
      "label": "41 Lee - NORTH",
      "routeId": "19612",
      "tripId": "3358432",
      "lat": 38.67137145996094,
      "lon": -90.2256088256836,
      "bearingDeg": 0,
      "speedMps": 0,
      "timestamp": 1779414639,
      "mode": "bus"
    },
    {
      "id": "6822",
      "label": "94 Page - WEST",
      "routeId": "19631",
      "tripId": "3361391",
      "lat": 38.692691802978516,
      "lon": -90.39969635009766,
      "bearingDeg": 0,
      "speedMps": 0,
      "timestamp": 1779414606,
      "mode": "bus"
    },
    {
      "id": "6827",
      "label": "35 Rock Road - WEST",
      "routeId": "19610",
      "tripId": "3358115",
      "lat": 38.7010498046875,
      "lon": -90.33209991455078,
      "bearingDeg": 0,
      "speedMps": 0,
      "timestamp": 1779414638,
      "mode": "bus"
    },
    {
      "id": "6837",
      "label": "91 Olive - WEST",
      "routeId": "19630",
      "tripId": "3361245",
      "lat": 38.67333984375,
      "lon": -90.41232299804688,
      "bearingDeg": 0,
      "speedMps": 0,
      "timestamp": 1779414626,
      "mode": "bus"
    },
    {
      "id": "6842",
      "label": "31 Chouteau - WEST",
      "routeId": "19606",
      "tripId": "3357724",
      "lat": 38.612430572509766,
      "lon": -90.3227310180664,
      "bearingDeg": 0,
      "speedMps": 0,
      "timestamp": 1779414597,
      "mode": "bus"
    },
    {
      "id": "6844",
      "label": "30 Arsenal - WEST",
      "routeId": "19605",
      "tripId": "3357621",
      "lat": 38.60615158081055,
      "lon": -90.28047943115234,
      "bearingDeg": 0,
      "speedMps": 0,
      "timestamp": 1779414644,
      "mode": "bus"
    },
    {
      "id": "6846",
      "label": "64 Lucas-Hunt - SOUTH",
      "routeId": "19621",
      "tripId": "3359455",
      "lat": 38.726959228515625,
      "lon": -90.22712707519531,
      "bearingDeg": 0,
      "speedMps": 0,
      "timestamp": 1779414645,
      "mode": "bus"
    },
    {
      "id": "6847",
      "label": "11 Chippewa - WEST",
      "routeId": "19599",
      "tripId": "3356728",
      "lat": 38.59008026123047,
      "lon": -90.26068878173828,
      "bearingDeg": 0,
      "speedMps": 0,
      "timestamp": 1779414619,
      "mode": "bus"
    },
    {
      "id": "6852",
      "label": "1 Main Street - State Street - WEST",
      "routeId": "19636",
      "tripId": "3362166",
      "lat": 38.54140853881836,
      "lon": -90.02455139160156,
      "bearingDeg": 0,
      "speedMps": 0,
      "timestamp": 1779414613,
      "mode": "bus"
    },
    {
      "id": "6901",
      "label": "31 Chouteau - EAST",
      "routeId": "19606",
      "tripId": "3357702",
      "lat": 38.626651763916016,
      "lon": -90.25919342041016,
      "bearingDeg": 0,
      "speedMps": 0,
      "timestamp": 1779414642,
      "mode": "bus"
    },
    {
      "id": "6904",
      "label": "95 Kingshighway - SOUTH",
      "routeId": "19632",
      "tripId": "3361553",
      "lat": 38.59328079223633,
      "lon": -90.27214813232422,
      "bearingDeg": 0,
      "speedMps": 0,
      "timestamp": 1779414631,
      "mode": "bus"
    },
    {
      "id": "6905",
      "label": "49 Lindbergh - SOUTH",
      "routeId": "19614",
      "tripId": "3358637",
      "lat": 38.71828079223633,
      "lon": -90.31614685058594,
      "bearingDeg": 0,
      "speedMps": 0,
      "timestamp": 1779414640,
      "mode": "bus"
    },
    {
      "id": "6910",
      "label": "49 Lindbergh - NORTH",
      "routeId": "19614",
      "tripId": "3358659",
      "lat": 38.67731857299805,
      "lon": -90.408203125,
      "bearingDeg": 0,
      "speedMps": 0,
      "timestamp": 1779414635,
      "mode": "bus"
    },
    {
      "id": "6911",
      "label": "70 Grand - NORTH",
      "routeId": "19622",
      "tripId": "3359784",
      "lat": 38.65584182739258,
      "lon": -90.22042083740234,
      "bearingDeg": 0,
      "speedMps": 0,
      "timestamp": 1779414594,
      "mode": "bus"
    },
    {
      "id": "6913",
      "label": "19 St Louis Ave - EAST",
      "routeId": "19603",
      "tripId": "3357329",
      "lat": 38.650970458984375,
      "lon": -90.20166778564453,
      "bearingDeg": 0,
      "speedMps": 0,
      "timestamp": 1779414629,
      "mode": "bus"
    },
    {
      "id": "6915",
      "label": "74 Florissant - SOUTH",
      "routeId": "19624",
      "tripId": "3360219",
      "lat": 38.62974166870117,
      "lon": -90.20057678222656,
      "bearingDeg": 0,
      "speedMps": 0,
      "timestamp": 1779414631,
      "mode": "bus"
    },
    {
      "id": "6919",
      "label": "79 Ferguson-Clayton - NORTH",
      "routeId": "19628",
      "tripId": "3360892",
      "lat": 38.69832992553711,
      "lon": -90.3284683227539,
      "bearingDeg": 0,
      "speedMps": 0,
      "timestamp": 1779414627,
      "mode": "bus"
    },
    {
      "id": "6922",
      "label": "79 Ferguson-Clayton - SOUTH",
      "routeId": "19628",
      "tripId": "3360866",
      "lat": 38.71963119506836,
      "lon": -90.30599975585938,
      "bearingDeg": 0,
      "speedMps": 0,
      "timestamp": 1779414629,
      "mode": "bus"
    },
    {
      "id": "6927",
      "label": "97 Delmar - EAST",
      "routeId": "19633",
      "tripId": "3361787",
      "lat": 38.65102005004883,
      "lon": -90.2568130493164,
      "bearingDeg": 0,
      "speedMps": 0,
      "timestamp": 1779414636,
      "mode": "bus"
    },
    {
      "id": "6940",
      "label": "32 Dr ML King - EAST",
      "routeId": "19607",
      "tripId": "3357833",
      "lat": 38.676979064941406,
      "lon": -90.28855895996094,
      "bearingDeg": 0,
      "speedMps": 0,
      "timestamp": 1779414642,
      "mode": "bus"
    },
    {
      "id": "6952",
      "label": "12 OFallon-Fairview Heights - EAST",
      "routeId": "19644",
      "tripId": "3363462",
      "lat": 38.59540939331055,
      "lon": -90.04576110839844,
      "bearingDeg": 0,
      "speedMps": 0,
      "timestamp": 1779414626,
      "mode": "bus"
    },
    {
      "id": "7004",
      "label": "70 Grand - SOUTH",
      "routeId": "19622",
      "tripId": "3359700",
      "lat": 38.658119201660156,
      "lon": -90.21885681152344,
      "bearingDeg": 0,
      "speedMps": 0,
      "timestamp": 1779414622,
      "mode": "bus"
    },
    {
      "id": "7007",
      "label": "95 Kingshighway - NORTH",
      "routeId": "19632",
      "tripId": "3361604",
      "lat": 38.58005905151367,
      "lon": -90.279541015625,
      "bearingDeg": 0,
      "speedMps": 0,
      "timestamp": 1779414646,
      "mode": "bus"
    },
    {
      "id": "7012",
      "label": "70 Grand - SOUTH",
      "routeId": "19622",
      "tripId": "3359699",
      "lat": 38.62042999267578,
      "lon": -90.23876953125,
      "bearingDeg": 0,
      "speedMps": 0,
      "timestamp": 1779414582,
      "mode": "bus"
    },
    {
      "id": "7014",
      "label": "10 Gravois-Lindell - NORTH",
      "routeId": "19598",
      "tripId": "3356480",
      "lat": 38.60078811645508,
      "lon": -90.23233795166016,
      "bearingDeg": 0,
      "speedMps": 0,
      "timestamp": 1779414637,
      "mode": "bus"
    },
    {
      "id": "7018",
      "label": "61 Chambers Rd - EAST",
      "routeId": "19620",
      "tripId": "3359226",
      "lat": 38.74745178222656,
      "lon": -90.22444915771484,
      "bearingDeg": 0,
      "speedMps": 0,
      "timestamp": 1779414626,
      "mode": "bus"
    },
    {
      "id": "7020",
      "label": "74 Florissant - NORTH",
      "routeId": "19624",
      "tripId": "3360275",
      "lat": 38.71255111694336,
      "lon": -90.25447845458984,
      "bearingDeg": 0,
      "speedMps": 0,
      "timestamp": 1779414621,
      "mode": "bus"
    },
    {
      "id": "7026",
      "label": "4 Natural Bridge - EAST",
      "routeId": "19594",
      "tripId": "3356103",
      "lat": 38.670570373535156,
      "lon": -90.2384262084961,
      "bearingDeg": 0,
      "speedMps": 0,
      "timestamp": 1779414625,
      "mode": "bus"
    },
    {
      "id": "7105",
      "label": "57 Manchester - WEST",
      "routeId": "19616",
      "tripId": "3358835",
      "lat": 38.59286117553711,
      "lon": -90.50457000732422,
      "bearingDeg": 0,
      "speedMps": 0,
      "timestamp": 1779414561,
      "mode": "bus"
    },
    {
      "id": "7107",
      "label": "4 Natural Bridge - WEST",
      "routeId": "19594",
      "tripId": "3356136",
      "lat": 38.687889099121094,
      "lon": -90.27359771728516,
      "bearingDeg": 0,
      "speedMps": 0,
      "timestamp": 1779414639,
      "mode": "bus"
    },
    {
      "id": "7112",
      "label": "97 Delmar - WEST",
      "routeId": "19633",
      "tripId": "3361807",
      "lat": 38.6526985168457,
      "lon": -90.27323150634766,
      "bearingDeg": 0,
      "speedMps": 0,
      "timestamp": 1779414612,
      "mode": "bus"
    },
    {
      "id": "7115",
      "label": "90 Hampton - NORTH",
      "routeId": "19629",
      "tripId": "3361037",
      "lat": 38.592559814453125,
      "lon": -90.29441833496094,
      "bearingDeg": 0,
      "speedMps": 0,
      "timestamp": 1779414628,
      "mode": "bus"
    },
    {
      "id": "7152",
      "label": "1 Main Street - State Street - WEST",
      "routeId": "19636",
      "tripId": "3362165",
      "lat": 38.59254837036133,
      "lon": -90.06659698486328,
      "bearingDeg": 0,
      "speedMps": 0,
      "timestamp": 1779414620,
      "mode": "bus"
    },
    {
      "id": "7201",
      "label": "73 Carondelet - NORTH",
      "routeId": "19623",
      "tripId": "3360105",
      "lat": 38.537940979003906,
      "lon": -90.28270721435547,
      "bearingDeg": 0,
      "speedMps": 0,
      "timestamp": 1779414644,
      "mode": "bus"
    },
    {
      "id": "7213",
      "label": "61 Chambers Rd - WEST",
      "routeId": "19620",
      "tripId": "3359272",
      "lat": 38.74882888793945,
      "lon": -90.33512115478516,
      "bearingDeg": 0,
      "speedMps": 0,
      "timestamp": 1779414649,
      "mode": "bus"
    },
    {
      "id": "7214",
      "label": "32 Dr ML King - WEST",
      "routeId": "19607",
      "tripId": "3357794",
      "lat": 38.66395950317383,
      "lon": -90.26396942138672,
      "bearingDeg": 0,
      "speedMps": 0,
      "timestamp": 1779414643,
      "mode": "bus"
    },
    {
      "id": "7216",
      "label": "91 Olive - EAST",
      "routeId": "19630",
      "tripId": "3361215",
      "lat": 38.6752815246582,
      "lon": -90.4622802734375,
      "bearingDeg": 0,
      "speedMps": 0,
      "timestamp": 1779414640,
      "mode": "bus"
    },
    {
      "id": "7252",
      "label": "1 Main Street - State Street - EAST",
      "routeId": "19636",
      "tripId": "3362224",
      "lat": 38.61838912963867,
      "lon": -90.13353729248047,
      "bearingDeg": 0,
      "speedMps": 0,
      "timestamp": 1779414598,
      "mode": "bus"
    },
    {
      "id": "7304",
      "label": "8 Shaw-Cherokee - SOUTH",
      "routeId": "19596",
      "tripId": "3356290",
      "lat": 38.63536834716797,
      "lon": -90.25968933105469,
      "bearingDeg": 0,
      "speedMps": 0,
      "timestamp": 1779414639,
      "mode": "bus"
    },
    {
      "id": "7305",
      "label": "33 Midland - EAST",
      "routeId": "19608",
      "tripId": "3357957",
      "lat": 38.65214157104492,
      "lon": -90.33384704589844,
      "bearingDeg": 0,
      "speedMps": 0,
      "timestamp": 1779414606,
      "mode": "bus"
    },
    {
      "id": "7309",
      "label": "76 N Hanley Shuttle - NORTH",
      "routeId": "19625",
      "tripId": "3360471",
      "lat": 38.79207992553711,
      "lon": -90.32408142089844,
      "bearingDeg": 0,
      "speedMps": 0,
      "timestamp": 1779414625,
      "mode": "bus"
    },
    {
      "id": "7311",
      "label": "2 Red - SOUTH",
      "routeId": "19593",
      "tripId": "3355969",
      "lat": 38.6634407043457,
      "lon": -90.31137084960938,
      "bearingDeg": 0,
      "speedMps": 0,
      "timestamp": 1779414644,
      "mode": "rail"
    },
    {
      "id": "7312",
      "label": "42 Sarah - NORTH",
      "routeId": "19613",
      "tripId": "3358560",
      "lat": 38.63587188720703,
      "lon": -90.24732208251953,
      "bearingDeg": 0,
      "speedMps": 0,
      "timestamp": 1779414642,
      "mode": "bus"
    },
    {
      "id": "7314",
      "label": "5 Green - CLOCKWISE",
      "routeId": "19595",
      "tripId": "3356255",
      "lat": 38.65153884887695,
      "lon": -90.31484985351562,
      "bearingDeg": 0,
      "speedMps": 0,
      "timestamp": 1779414627,
      "mode": "bus"
    },
    {
      "id": "7316",
      "label": "41 Lee - SOUTH",
      "routeId": "19612",
      "tripId": "3358414",
      "lat": 38.66712188720703,
      "lon": -90.21607971191406,
      "bearingDeg": 0,
      "speedMps": 0,
      "timestamp": 1779414648,
      "mode": "bus"
    },
    {
      "id": "7317",
      "label": "60 Shepley-Lilac - SOUTH",
      "routeId": "19619",
      "tripId": "3359114",
      "lat": 38.769081115722656,
      "lon": -90.2750015258789,
      "bearingDeg": 0,
      "speedMps": 0,
      "timestamp": 1779414646,
      "mode": "bus"
    },
    {
      "id": "7321",
      "label": "1 Gold - WEST",
      "routeId": "19592",
      "tripId": "3355871",
      "lat": 38.64651870727539,
      "lon": -90.3065414428711,
      "bearingDeg": 0,
      "speedMps": 0,
      "timestamp": 1779414631,
      "mode": "bus"
    },
    {
      "id": "7354",
      "label": "6 Rosemont - WEST",
      "routeId": "19641",
      "tripId": "3362940",
      "lat": 38.597511291503906,
      "lon": -90.06448364257812,
      "bearingDeg": 0,
      "speedMps": 0,
      "timestamp": 1779414215,
      "mode": "bus"
    },
    {
      "id": "7505",
      "label": "13 Union - SOUTH",
      "routeId": "19600",
      "tripId": "3356932",
      "lat": 38.69281005859375,
      "lon": -90.24315643310547,
      "bearingDeg": 0,
      "speedMps": 0,
      "timestamp": 1779414642,
      "mode": "bus"
    },
    {
      "id": "7506",
      "label": "2 Red - NORTH",
      "routeId": "19593",
      "tripId": "3355980",
      "lat": 38.6273307800293,
      "lon": -90.33799743652344,
      "bearingDeg": 0,
      "speedMps": 0,
      "timestamp": 1779414586,
      "mode": "rail"
    },
    {
      "id": "7513",
      "label": "35 Rock Road - EAST",
      "routeId": "19610",
      "tripId": "3358079",
      "lat": 38.7413215637207,
      "lon": -90.40577697753906,
      "bearingDeg": 0,
      "speedMps": 0,
      "timestamp": 1779414635,
      "mode": "bus"
    },
    {
      "id": "7514",
      "label": "18 Taylor - NORTH",
      "routeId": "19602",
      "tripId": "3357199",
      "lat": 38.642120361328125,
      "lon": -90.258056640625,
      "bearingDeg": 0,
      "speedMps": 0,
      "timestamp": 1779414624,
      "mode": "bus"
    },
    {
      "id": "7552",
      "label": "3 Sauget - Water Street - SOUTH",
      "routeId": "19638",
      "tripId": "3362637",
      "lat": 38.5725212097168,
      "lon": -90.18781280517578,
      "bearingDeg": 0,
      "speedMps": 0,
      "timestamp": 1779414614,
      "mode": "bus"
    },
    {
      "id": "7560",
      "label": "13 Caseyville - NORTH",
      "routeId": "19645",
      "tripId": "3363672",
      "lat": 38.63383865356445,
      "lon": -90.02803802490234,
      "bearingDeg": 0,
      "speedMps": 0,
      "timestamp": 1779414624,
      "mode": "bus"
    },
    {
      "id": "7562",
      "label": "16 St. Clair Square - SOUTH",
      "routeId": "19648",
      "tripId": "3363914",
      "lat": 38.59300994873047,
      "lon": -89.98503875732422,
      "bearingDeg": 0,
      "speedMps": 0,
      "timestamp": 1779414591,
      "mode": "bus"
    },
    {
      "id": "7563",
      "label": "2 Cahokia Heights - NORTH",
      "routeId": "19637",
      "tripId": "3362417",
      "lat": 38.60218048095703,
      "lon": -90.17237091064453,
      "bearingDeg": 0,
      "speedMps": 0,
      "timestamp": 1779414618,
      "mode": "bus"
    },
    {
      "id": "7564",
      "label": "8 Alta Sita - NORTH",
      "routeId": "19642",
      "tripId": "3363139",
      "lat": 38.558860778808594,
      "lon": -90.17204284667969,
      "bearingDeg": 0,
      "speedMps": 0,
      "timestamp": 1779414545,
      "mode": "bus"
    },
    {
      "id": "7572",
      "label": "15 Belleville-O'Fallon - WEST",
      "routeId": "19647",
      "tripId": "3363794",
      "lat": 38.522579193115234,
      "lon": -89.97966003417969,
      "bearingDeg": 0,
      "speedMps": 0,
      "timestamp": 1779414619,
      "mode": "bus"
    },
    {
      "id": "7573",
      "label": "14 Memorial Hosp-Westfield Plaza - EAST",
      "routeId": "19646",
      "tripId": "3363751",
      "lat": 38.55168914794922,
      "lon": -90.02615356445312,
      "bearingDeg": 0,
      "speedMps": 0,
      "timestamp": 1779414492,
      "mode": "bus"
    },
    {
      "id": "7660",
      "label": "9 Washington Park - EAST",
      "routeId": "19643",
      "tripId": "3363296",
      "lat": 38.636810302734375,
      "lon": -90.09384155273438,
      "bearingDeg": 0,
      "speedMps": 0,
      "timestamp": 1779414621,
      "mode": "bus"
    }
  ]
}
